hyperhdr/__init__.py
hyperhdr/client.py
hyperhdr/const.py
hyperhdr/py.typed
LICENSE
hyperhdr_py-0.0.3.dist-info/LICENSE
hyperhdr_py-0.0.3.dist-info/WHEEL
hyperhdr_py-0.0.3.dist-info/METADATA
hyperhdr_py-0.0.3.dist-info/RECORD
