Metadata-Version: 2.1
Name: hyperhdr-py
Version: 0.0.3
Summary: HyperHDR Ambient Lighting Python Package
Home-page: https://github.com/mjoshd/hyperhdr-py
License: MIT
Keywords: hyperhdr
Author: mjoshd
Author-email: mjoshd@live.com
Requires-Python: >=3.8,<4.0
Classifier: Intended Audience :: Developers
Classifier: License :: OSI Approved :: MIT License
Classifier: Operating System :: OS Independent
Classifier: Programming Language :: Python :: 3
Classifier: Programming Language :: Python :: 3.10
Classifier: Programming Language :: Python :: 3.8
Classifier: Programming Language :: Python :: 3.9
Classifier: Topic :: Home Automation
Project-URL: Repository, https://github.com/mjoshd/hyperhdr-py
